adminconsult/__init__.py
adminconsult/api/__init__.py
adminconsult/api/base.py
adminconsult/api/clientcredentials.py
adminconsult/api/entity.py
adminconsult/api/entity_changes.py
adminconsult/api/entity_collection.py
adminconsult/api/admin/__init__.py
adminconsult/api/admin/changes.py
adminconsult/api/customer/__init__.py
adminconsult/api/customer/customer.py
adminconsult/api/customer/customer_address.py
adminconsult/api/customer/customer_address_changes.py
adminconsult/api/customer/customer_changes.py
adminconsult/api/customer/customer_email_data.py
adminconsult/api/customer/customer_email_data_changes.py
adminconsult/api/customer/customer_juridical.py
adminconsult/api/customer/customer_link_customer.py
adminconsult/api/customer/customer_link_customer_changes.py
adminconsult/api/customer/customer_private.py
adminconsult/api/dms/__init__.py
adminconsult/api/expensedeclaration/__init__.py
adminconsult/api/expensedeclaration/expense_declaration.py
adminconsult/api/expensedeclaration/expense_item.py
adminconsult/api/externalfile/__init__.py
adminconsult/api/extrafield/__init__.py
adminconsult/api/extrafield/extra_column.py
adminconsult/api/extrafield/extra_data.py
adminconsult/api/extrafield/extra_table.py
adminconsult/api/financial/__init__.py
adminconsult/api/hrm/__init__.py
adminconsult/api/hrm/employee.py
adminconsult/api/hrm/employee_profile.py
adminconsult/api/hrm/planning.py
adminconsult/api/lists/__init__.py
adminconsult/api/lists/countries.py
adminconsult/api/lists/list.py
adminconsult/api/lists/nacecodes.py
adminconsult/api/lists/named_lists.py
adminconsult/api/lists/titles.py
adminconsult/api/organization/__init__.py
adminconsult/api/organization/company.py
adminconsult/api/organization/department.py
adminconsult/api/pricegrid/__init__.py
adminconsult/api/pricegrid/pricegrid.py
adminconsult/api/pricegrid/pricegrid_details.py
adminconsult/api/productuse/__init__.py
adminconsult/api/productuse/product_category.py
adminconsult/api/productuse/product_item.py
adminconsult_sdk-1.0.7.dist-info/licenses/LICENSE
adminconsult_sdk-1.0.7.dist-info/METADATA
adminconsult_sdk-1.0.7.dist-info/WHEEL
adminconsult_sdk-1.0.7.dist-info/top_level.txt
adminconsult_sdk-1.0.7.dist-info/RECORD
