Metadata-Version: 2.4
Name: adminconsult_sdk
Version: 1.0.7
Summary: Syneton Admin Consult SDK - REST API Wrapper
Home-page: https://github.com/cornettew/adminconsult-sdk
Author: Ward Cornette
Author-email: Ward.Cornette@num3rix.fr
Classifier: Programming Language :: Python :: 3
Classifier: Operating System :: OS Independent
Requires-Python: >=3.7
License-File: LICENSE
Requires-Dist: pandas
Requires-Dist: regex
Requires-Dist: hvac
Requires-Dist: requests
Requires-Dist: SQLAlchemy
Requires-Dist: sqlalchemy-sqlany
Requires-Dist: psycopg2-binary
Dynamic: author
Dynamic: author-email
Dynamic: classifier
Dynamic: description
Dynamic: description-content-type
Dynamic: home-page
Dynamic: license-file
Dynamic: requires-dist
Dynamic: requires-python
Dynamic: summary
